AUTHORS
LICENSE
MANIFEST.in
README.rst
runtests.py
setup.py
tox.ini
django_exmodel.egg-info/PKG-INFO
django_exmodel.egg-info/SOURCES.txt
django_exmodel.egg-info/dependency_links.txt
django_exmodel.egg-info/not-zip-safe
django_exmodel.egg-info/requires.txt
django_exmodel.egg-info/top_level.txt
exmodel/__init__.py
exmodel/base.py
tests/.tests.py.swp
tests/__init__.py
tests/__init__.pyc
tests/tests.py
tests/tests.pyc
tests/__pycache__/__init__.cpython-34.pyc
tests/__pycache__/tests.cpython-34.pyc