Metadata-Version: 1.1
Name: django-exmodel
Version: 0.0.2
Summary: Makes your Django models extendable.
Home-page: http://github.com/sorl/django-exmodel
Author: Mikko Hellsing
Author-email: mikko@aino.com
License: ICS
Platform: UNKNOWN
Classifier: Development Status :: 3 - Alpha
Classifier: Environment :: Web Environment
Classifier: Intended Audience :: Developers
Classifier: License :: OSI Approved :: ISC License (ISCL)
Classifier: Operating System :: OS Independent
Classifier: Programming Language :: Python
Classifier: Programming Language :: Python :: 2.7
Classifier: Programming Language :: Python :: 3.4
Classifier: Framework :: Django
